ibm_cloud_browser_mcp/__init__.py
ibm_cloud_browser_mcp-0.1.0.dist-info/METADATA
ibm_cloud_browser_mcp-0.1.0.dist-info/WHEEL
ibm_cloud_browser_mcp-0.1.0.dist-info/entry_points.txt
ibm_cloud_browser_mcp-0.1.0.dist-info/RECORD
