Metadata-Version: 2.4
Name: ibm-cloud-browser-mcp
Version: 0.1.0
Summary: MCP server to open IBM Cloud console in browser
Project-URL: Homepage, https://github.com/jon13w/ibm-cloud-browser-mcp
Project-URL: Repository, https://github.com/jon13w/ibm-cloud-browser-mcp
Project-URL: Issues, https://github.com/jon13w/ibm-cloud-browser-mcp/issues
Author-email: Jon Woodlief <jon13w@gmail.com>
License: MIT
Classifier: Development Status :: 3 - Alpha
Classifier: Intended Audience :: Developers
Classifier: License :: OSI Approved :: MIT License
Classifier: Programming Language :: Python :: 3
Classifier: Programming Language :: Python :: 3.10
Classifier: Programming Language :: Python :: 3.11
Classifier: Programming Language :: Python :: 3.12
Classifier: Topic :: Software Development :: Libraries :: Python Modules
Requires-Python: >=3.10
Requires-Dist: fastmcp
Requires-Dist: marionette-driver>=3.4.0
Requires-Dist: requests>=2.32.4
